Metadata-Version: 1.0
Name: qn2-sig
Version: 0.1.1
Summary: signal processing tools
Home-page: http://www.tem.uoc.gr/~kesmarag
Author: Costas Smaragdakis
Author-email: kesmarag@gmail.com
License: UNKNOWN
Platform: UNKNOWN
